luna_device_connections/luna_ssh_connection.py
luna_device_connections/luna_console_connection.py
luna_device_connections/exceptions.py
luna_device_connections/luna_adapter.py
luna_device_connections/luna_outputs.py
luna_device_connections/__init__.py
device_connections/device_connection.py
device_connections/hsm_credential_provider.py
device_connections/base_adapter.py
device_connections/__init__.py
luna_manipulator/luna_appliance_manipulator.py
luna_manipulator/luna_manipulating_adapter_53.py
luna_manipulator/luna_manipulating_adapter.py
luna_manipulator/luna_manipulating_adapter_54.py
luna_manipulator/__init__.py
luna_reader/luna_reading_adapter_54.py
luna_reader/luna_state_reader.py
luna_reader/exceptions.py
luna_reader/luna_reading_adapter_53.py
luna_reader/luna_reading_adapter.py
luna_reader/__init__.py
cloudhsmcli/hapg_cloner.py
cloudhsmcli/hapg_adder.py
cloudhsmcli/hsm_worker.py
cloudhsmcli/client_deregisterer.py
cloudhsmcli/hsm_initializer.py
cloudhsmcli/client_registerer.py
cloudhsmcli/hsm_cloner.py
cloudhsmcli/exceptions.py
cloudhsmcli/api.py
cloudhsmcli/hapg_remover.py
cloudhsmcli/dispatch.py
cloudhsmcli/errorcodes.json
cloudhsmcli/main.py
cloudhsmcli/parser.py
cloudhsmcli/__init__.py
cloudhsmcli/util.py
aws_cloudhsm_cli-3.0.8.dist-info/METADATA
aws_cloudhsm_cli-3.0.8.dist-info/RECORD
aws_cloudhsm_cli-3.0.8.dist-info/entry_points.txt
aws_cloudhsm_cli-3.0.8.dist-info/metadata.json
aws_cloudhsm_cli-3.0.8.dist-info/top_level.txt
aws_cloudhsm_cli-3.0.8.dist-info/DESCRIPTION.rst
aws_cloudhsm_cli-3.0.8.dist-info/WHEEL
