Metadata-Version: 2.0
Name: aws-cloudhsm-cli
Version: 3.0.8
Summary: Command line interface to CloudHSM
Home-page: http://aws.amazon.com/cloudhsm/
Author: The CloudHSM Team
Author-email: aws-cloudhsm-support@amazon.com
License: Apache License 2.0 http://aws.amazon.com/apache2.0/
Platform: UNKNOWN
Classifier: Development Status :: 5 - Production/Stable
Classifier: License :: OSI Approved :: Apache Software License
Classifier: Programming Language :: Python :: 2.7
Classifier: Programming Language :: Python :: 2 :: Only
Requires-Dist: setuptools
Requires-Dist: boto (>=2.27)
Requires-Dist: pexpect (>=2.3)
